cnspy_script_utils/__init__.py
cnspy_script_utils/directory_info.py
cnspy_script_utils/string_parser.py
cnspy_script_utils/utils.py
test/__init__.py
test/test_StringParser.py
test/test_directory_info.py
cnspy_script_utils-0.1.2.dist-info/LICENCE
cnspy_script_utils-0.1.2.dist-info/METADATA
cnspy_script_utils-0.1.2.dist-info/WHEEL
cnspy_script_utils-0.1.2.dist-info/top_level.txt
cnspy_script_utils-0.1.2.dist-info/RECORD
