Metadata-Version: 2.1
Name: cnspy_script_utils
Version: 0.1.2
Summary: Utilty scripts and functions.
Home-page: https://github.com/aau-cns/cnspy_script_utils/
Author: Roland Jung
Author-email: roland.jung@aau.at
Project-URL: Bug Tracker, https://github.com/aau-cns/cnspy_script_utils/issues
Classifier: Development Status :: 4 - Beta
Classifier: Intended Audience :: Developers
Classifier: Programming Language :: Python :: 3
Classifier: License :: OSI Approved :: GNU General Public License v3 (GPLv3)
Classifier: Operating System :: OS Independent
Requires-Python: >=3.6
License-File: LICENCE
